{
  "codeReview": {
    "by": "lazycodex-code-reviewer",
    "recommendation": "APPROVE",
    "codeQualityStatus": "CLEAR",
    "reportPath": ".omo/evidence/plan008-final-code-review.md",
    "evidence": "Final rerun code review approved after strict no-excuse cleanup. Non-blocking watch notes are documented in the report; no blockers remain.",
    "blockers": []
  },
  "manualQa": {
    "by": "lazycodex-qa-executor",
    "status": "passed",
    "evidence": "CLI/data surfaces passed for behavioral RED/GREEN, focused tests, full API tests, lint, compile, imports, greps, and scope baseline.",
    "surfaceEvidence": [
      {
        "id": "plan008-red-green",
        "criterionRef": "C001",
        "surface": "cli",
        "invocation": "temporary c6eb4db worktree plus final test file, then final focused pytest",
        "verdict": "passed",
        "artifactRefs": [
          "artifact-plan008-red-green"
        ]
      },
      {
        "id": "plan008-focused",
        "criterionRef": "C001",
        "surface": "cli",
        "invocation": "python -m pytest apps/api/tests/test_transcoder_hwaccel.py -q",
        "verdict": "passed",
        "artifactRefs": [
          "artifact-plan008-manual-qa"
        ]
      },
      {
        "id": "plan008-full",
        "criterionRef": "C002",
        "surface": "cli",
        "invocation": "python -m pytest apps/api/tests -q",
        "verdict": "passed",
        "artifactRefs": [
          "artifact-plan008-manual-qa"
        ]
      },
      {
        "id": "plan008-static",
        "criterionRef": "C002",
        "surface": "cli",
        "invocation": "no-excuse checker, ruff, py_compile, import/settings, git diff --check, package-boundary greps",
        "verdict": "passed",
        "artifactRefs": [
          "artifact-plan008-manual-qa",
          "artifact-plan008-scope",
          "artifact-plan008-strict-cleanup"
        ]
      }
    ],
    "adversarialCases": [
      {
        "id": "hardware-absent",
        "criterionRef": "C001",
        "scenario": "No real GPU or hardware encoder is required; tests use monkeypatches and pure command builders.",
        "expectedBehavior": "Focused tests pass without device access.",
        "verdict": "passed",
        "artifactRefs": [
          "artifact-plan008-manual-qa"
        ]
      },
      {
        "id": "partial-output",
        "criterionRef": "C001",
        "scenario": "Hardware encode failure leaves partial HLS output before fallback.",
        "expectedBehavior": "Partial output is removed before software retry.",
        "verdict": "passed",
        "artifactRefs": [
          "artifact-plan008-manual-qa"
        ]
      },
      {
        "id": "dirty-worktree",
        "criterionRef": "C003",
        "scenario": "Out-of-scope dirty paths are visible in git status.",
        "expectedBehavior": "Scope artifact records baseline instead of reverting unrelated state.",
        "verdict": "passed",
        "artifactRefs": [
          "artifact-plan008-dirty-baseline",
          "artifact-plan008-scope"
        ]
      },
      {
        "id": "strict-quality",
        "criterionRef": "C002",
        "scenario": "No-excuse checker runs on touched Plan 008 Python files.",
        "expectedBehavior": "Checker reports no violations and test module stays at or below 250 pure LOC.",
        "verdict": "passed",
        "artifactRefs": [
          "artifact-plan008-strict-cleanup"
        ]
      }
    ],
    "artifactRefs": [
      {
        "id": "artifact-plan008-red-green",
        "kind": "cli-transcript",
        "description": "Behavioral RED/GREEN transcript using temporary baseline worktree.",
        "path": ".omo/ulw-loop/evidence/008-c001b-behavioral-red-green.txt"
      },
      {
        "id": "artifact-plan008-manual-qa",
        "kind": "log",
        "description": "Final manual QA report.",
        "path": ".omo/ulw-loop/evidence/plan008-final-manual-qa.md"
      },
      {
        "id": "artifact-plan008-scope",
        "kind": "log",
        "description": "Final scope review.",
        "path": ".omo/ulw-loop/evidence/plan008-final-scope.md"
      },
      {
        "id": "artifact-plan008-dirty-baseline",
        "kind": "data-diff",
        "description": "Dirty worktree baseline receipt.",
        "path": ".omo/ulw-loop/evidence/plan008-preexisting-dirty-baseline.txt"
      },
      {
        "id": "artifact-plan008-qa-review",
        "kind": "log",
        "description": "QA review report.",
        "path": ".omo/evidence/plan008-qa-review.md"
      },
      {
        "id": "artifact-plan008-strict-cleanup",
        "kind": "cli-transcript",
        "description": "Strict programming/no-excuse cleanup verification.",
        "path": ".omo/ulw-loop/evidence/plan008-strict-cleanup-verification.txt"
      }
    ]
  },
  "gateReview": {
    "by": "lazycodex-gate-reviewer",
    "recommendation": "APPROVE",
    "reportPath": ".omo/evidence/plan008-final-gate-review.md",
    "evidence": "Final gate rerun approved; no-excuse checker, focused tests, full API suite, ruff, py_compile, import/settings sanity, package-boundary greps, and diff check passed.",
    "blockers": []
  },
  "iteration": {
    "fullRerun": true,
    "status": "passed",
    "rerunCommands": [
      "python -m pytest apps/api/tests/test_transcoder_hwaccel.py -q -k 'resolve_backend or select_backend'",
      "python -m pytest apps/api/tests/test_transcoder_hwaccel.py -q",
      "python -m pytest apps/api/tests -q",
      "rtk uvx ruff check packages/transcoder/hwaccel.py packages/transcoder/ffmpeg_transcoder.py apps/api/config.py apps/api/tasks/transcode_tasks.py apps/api/tests/test_transcoder_hwaccel.py",
      "python -m py_compile packages/transcoder/hwaccel.py packages/transcoder/ffmpeg_transcoder.py apps/api/config.py apps/api/tasks/transcode_tasks.py apps/api/tests/test_transcoder_hwaccel.py"
    ],
    "evidence": "Final reruns passed after strict no-excuse cleanup and reviewer/gate reruns approved."
  },
  "criteriaCoverage": {
    "totalCriteria": 3,
    "passCount": 3,
    "originalIntent": "Execute Plan 008 hardware-accelerated transcode with settings, fallback, tests, evidence, and reviewer approval.",
    "desiredOutcome": "FFmpeg transcoder selects configured or auto hardware H.264 backend, falls back to software safely, preserves software HLS output shape, and remains package-boundary clean.",
    "userOutcomeReview": "Current source satisfies the requested behavior; all CLI/data verification surfaces pass; final code, QA, and gate reviewers approved.",
    "adversarialClassesCovered": [
      "stale_state",
      "dirty_worktree",
      "hardware_absent",
      "partial_output",
      "package_boundary",
      "misleading_success_output",
      "hung_or_long_commands",
      "strict_quality"
    ]
  }
}
